freenom_dns_updater/__init__.py
freenom_dns_updater/config.py
freenom_dns_updater/domain.py
freenom_dns_updater/domain_parser.py
freenom_dns_updater/encrypted_string.py
freenom_dns_updater/freenom.py
freenom_dns_updater/freenom_session.py
freenom_dns_updater/get_my_ip.py
freenom_dns_updater/record.py
freenom_dns_updater/record_parser.py
freenom_dns_updater/exception/__init__.py
freenom_dns_updater/exception/add_error.py
freenom_dns_updater/exception/dns_record_base_exception.py
freenom_dns_updater/exception/remove_error.py
freenom_dns_updater/exception/update_error.py
freenom_dns_updater/scripts/__init__.py
freenom_dns_updater/scripts/fdu.py
freenom_dns_updater/test/__init__.py
freenom_dns_updater/test/test_config.py
freenom_dns_updater/test/test_domain_parser.py
freenom_dns_updater/test/test_encrypt_string.py
freenom_dns_updater/test/test_freenom.py
freenom_dns_updater/test/test_get_my_ip.py
freenom_dns_updater/test/test_record_parser.py
freenom_dns_updater-1.2.9.dist-info/LICENSE.txt
freenom_dns_updater-1.2.9.dist-info/METADATA
freenom_dns_updater-1.2.9.dist-info/WHEEL
freenom_dns_updater-1.2.9.dist-info/entry_points.txt
freenom_dns_updater-1.2.9.dist-info/top_level.txt
freenom_dns_updater-1.2.9.dist-info/RECORD
