Metadata-Version: 2.1
Name: freenom-dns-updater
Version: 1.2.9
Summary: A tool to update freenom's dns records
Home-page: https://github.com/maxisoft/Freenom-dns-updater
Author: maxisoft
Author-email: maxisoft@maxisoft.ga
License: MIT
Keywords: freenom dns
Platform: UNKNOWN
Classifier: Development Status :: 4 - Beta
Classifier: Intended Audience :: Developers
Classifier: Topic :: Software Development :: Build Tools
Classifier: License :: OSI Approved :: MIT License
Classifier: Programming Language :: Python :: 3
Classifier: Programming Language :: Python :: 3.8
Requires-Python: ~=3.6
Requires-Dist: requests
Requires-Dist: beautifulsoup4
Requires-Dist: PyYAML
Requires-Dist: six
Requires-Dist: click
Requires-Dist: oscrypto
Provides-Extra: dev
Requires-Dist: check-manifest ; extra == 'dev'
Provides-Extra: test
